[{"渠道": "华盛", "品牌": "黑马", "种类": "滤嘴", "规格": "8*22mm 8*2mm", "个数": "60pcs", "不加税价格 (¥)": "8.82", "含税价格 (¥)": "13.23", "美元价格 ($)": "1.30", "库存": "无货", "口味/描述": "黑马常规长滤嘴 Dark Horse Regular Long Filter 8*22mm 60pcs"}, {"渠道": "华盛", "品牌": "T&T", "种类": "滤嘴", "规格": "6*15mm", "个数": "120pcs", "不加税价格 (¥)": "8.93", "含税价格 (¥)": "13.39", "美元价格 ($)": "1.32", "库存": "无货", "口味/描述": "T&T 超细滤嘴 T&T Slim Filter Tips 6*15 120pcs"}, {"渠道": "华盛", "品牌": "T&T", "种类": "滤嘴", "规格": "6*22mm 6*2mm", "个数": "120pcs", "不加税价格 (¥)": "8.93", "含税价格 (¥)": "13.39", "美元价格 ($)": "1.32", "库存": "有货", "口味/描述": "T&T 常规长滤嘴 T&T Regular Long Filter 6*22mm 120pcs"}, {"渠道": "华盛", "品牌": "T&T", "种类": "滤嘴", "规格": "8*22mm 8*2mm", "个数": "100pcs", "不加税价格 (¥)": "8.93", "含税价格 (¥)": "13.39", "美元价格 ($)": "1.32", "库存": "有货", "口味/描述": "T&T 常规长滤嘴 T&T Regular Long Filter 8*22mm 100pcs"}, {"渠道": "华盛", "品牌": "T&T", "种类": "滤嘴", "规格": "8*15mm 8*1mm", "个数": "100pcs", "不加税价格 (¥)": "8.93", "含税价格 (¥)": "13.39", "美元价格 ($)": "1.32", "库存": "有货", "口味/描述": "T&T 常规细长滤嘴 T&T Regular Filter Tips Filter 8*15mm 100pcs"}, {"渠道": "华盛", "品牌": "老人牌", "种类": "滤嘴", "规格": "8*15mm 8*1mm", "个数": "100pcs", "不加税价格 (¥)": "9.43", "含税价格 (¥)": "14.14", "美元价格 ($)": "1.39", "库存": "有货", "口味/描述": "老人牌常规滤嘴 Zig Zag Regular Filter Tips 8*15mm 100pcs"}, {"渠道": "华盛", "品牌": "老人牌", "种类": "滤嘴", "规格": "6*22mm 6*2mm", "个数": "100pcs", "不加税价格 (¥)": "9.43", "含税价格 (¥)": "14.14", "美元价格 ($)": "1.39", "库存": "有货", "口味/描述": "老人牌细滤嘴 Zig Zag Slim Filter 6*22mm 100pcs"}, {"渠道": "华盛", "品牌": "虎牌", "种类": "滤嘴", "规格": "6*15mm 6*1mm", "个数": "", "不加税价格 (¥)": "9.69", "含税价格 (¥)": "14.54", "美元价格 ($)": "1.43", "库存": "有货", "口味/描述": "虎牌6毫米滤嘴 Mascotte Slim Filter  6*15mm"}, {"渠道": "华盛", "品牌": "虎牌", "种类": "滤嘴", "规格": "7*15mm 7*1mm", "个数": "", "不加税价格 (¥)": "9.69", "含税价格 (¥)": "14.54", "美元价格 ($)": "1.43", "库存": "有货", "口味/描述": "虎牌7毫米滤嘴 Mascotte Regular Filter 7*15mm"}, {"渠道": "华盛", "品牌": "老人牌", "种类": "滤嘴", "规格": "5*15mm 5*1mm", "个数": "150pcs", "不加税价格 (¥)": "10.11", "含税价格 (¥)": "15.16", "美元价格 ($)": "1.49", "库存": "有货", "口味/描述": "老人牌细滤嘴 Zig Zag Ultra Slim Filter 5*15mm 150pcs"}, {"渠道": "华盛", "品牌": "煙先生", "种类": "滤嘴", "规格": "6*15mm 6*1mm", "个数": "120pcs", "不加税价格 (¥)": "10.64", "含税价格 (¥)": "15.96", "美元价格 ($)": "1.57", "库存": "无货", "口味/描述": "烟先生细长滤嘴 Smoking Slim Filter 6*15mm 120pcs"}, {"渠道": "华盛", "品牌": "煙先生", "种类": "滤嘴", "规格": "5.7*14mm 5.7*1mm", "个数": "120pcs", "不加税价格 (¥)": "11.02", "含税价格 (¥)": "16.53", "美元价格 ($)": "1.62", "库存": "无货", "口味/描述": "烟先生特细滤嘴 Smoking Ultra Slim Filter 5.7*14 mm 120pcs"}, {"渠道": "华盛", "品牌": "黑马", "种类": "滤嘴", "规格": "8*15mm 8*1mm", "个数": "", "不加税价格 (¥)": "11.47", "含税价格 (¥)": "17.21", "美元价格 ($)": "1.69", "库存": "有货", "口味/描述": "黑马薄荷常规滤嘴 Dark Horse Regular Filter Menthol 8*15mm"}, {"渠道": "华盛", "品牌": "黑马", "种类": "滤嘴", "规格": "6*22mm 6*2mm", "个数": "", "不加税价格 (¥)": "11.47", "含税价格 (¥)": "17.21", "美元价格 ($)": "1.69", "库存": "无货", "口味/描述": "黑马薄荷长细滤嘴 Dark Horse Menthol Slim Long Filter Tips 6*22mm"}, {"渠道": "华盛", "品牌": "黑马", "种类": "滤嘴", "规格": "6*15mm 6*1mm", "个数": "", "不加税价格 (¥)": "11.53", "含税价格 (¥)": "17.29", "美元价格 ($)": "1.70", "库存": "无货", "口味/描述": "黑马细滤嘴 Dark Horse Slim Filter Menthol 6*15mm"}, {"渠道": "华盛", "品牌": "黑马", "种类": "滤嘴", "规格": "6*22mm 6*2mm", "个数": "100s", "不加税价格 (¥)": "11.53", "含税价格 (¥)": "17.29", "美元价格 ($)": "1.70", "库存": "无货", "口味/描述": "黑马长细长滤嘴 Dark Horse slim long filter 6*22mm 100s"}, {"渠道": "华盛", "品牌": "黑马", "种类": "滤嘴", "规格": "7*15mm 7*1mm", "个数": "", "不加税价格 (¥)": "11.53", "含税价格 (¥)": "17.29", "美元价格 ($)": "1.70", "库存": "有货", "口味/描述": "黑马细滤嘴 Dark Horse Slim Filter 7*15mm"}, {"渠道": "华盛", "品牌": "黑马", "种类": "滤嘴", "规格": "6*15mm 6*1mm", "个数": "", "不加税价格 (¥)": "11.53", "含税价格 (¥)": "17.29", "美元价格 ($)": "1.70", "库存": "有货", "口味/描述": "黑马细滤嘴 Dark Horse Slim Filter 6*15mm"}, {"渠道": "华盛", "品牌": "煙先生", "种类": "滤嘴", "规格": "7.5*15mm 7.5*1mm", "个数": "120pcs", "不加税价格 (¥)": "11.58", "含税价格 (¥)": "17.37", "美元价格 ($)": "1.71", "库存": "无货", "口味/描述": "烟先生常规滤嘴 Smoking Regular Filter 7.5*15mm 120pcs"}, {"渠道": "华盛", "品牌": "老人牌", "种类": "滤嘴", "规格": "6*15mm 6*1mm", "个数": "150pcs", "不加税价格 (¥)": "12.10", "含税价格 (¥)": "18.15", "美元价格 ($)": "1.78", "库存": "有货", "口味/描述": "老人牌细滤嘴 Zig Zag Slim Filter Tips 6*15mm 150pcs"}, {"渠道": "华盛", "品牌": "老人牌", "种类": "滤嘴", "规格": "6*15mm 6*1mm", "个数": "150pcs", "不加税价格 (¥)": "12.10", "含税价格 (¥)": "18.15", "美元价格 ($)": "1.78", "库存": "有货", "口味/描述": "老人牌薄荷细滤嘴 Zig Zag Menthol Slim Filter 6*15mm 150pcs"}, {"渠道": "华盛", "品牌": "黑马", "种类": "滤嘴", "规格": "6*15mm 6*1mm", "个数": "", "不加税价格 (¥)": "13.31", "含税价格 (¥)": "19.96", "美元价格 ($)": "1.96", "库存": "有货", "口味/描述": "黑马薄荷爆珠滤嘴 Dark Horse Menthol Crush Filter 6*15mm"}, {"渠道": "华盛", "品牌": "极限常规长滤嘴", "种类": "滤嘴", "规格": "8*22mm 8*2mm", "个数": "130pcs", "不加税价格 (¥)": "13.46", "含税价格 (¥)": "20.19", "美元价格 ($)": "1.98", "库存": "有货", "口味/描述": "极限常规长滤嘴 Extreme Regular Long Filter 8*22mm 130pcs"}, {"渠道": "华盛", "品牌": "极限细长滤嘴", "种类": "滤嘴", "规格": "6*22mm 6*2mm", "个数": "180pcs", "不加税价格 (¥)": "13.46", "含税价格 (¥)": "20.19", "美元价格 ($)": "1.98", "库存": "有货", "口味/描述": "极限细长滤嘴 Extreme Slim Long Filter 6*22mm 180pcs"}, {"渠道": "华盛", "品牌": "黑马", "种类": "滤嘴", "规格": "6*15mm 6*1mm", "个数": "", "不加税价格 (¥)": "14.19", "含税价格 (¥)": "21.29", "美元价格 ($)": "2.09", "库存": "无货", "口味/描述": "黑马碳细滤嘴 Dark Horse Slim Filter Charcoal Carbon 6*15mm"}, {"渠道": "华盛", "品牌": "煙先生", "种类": "滤嘴", "规格": "6*22mm 6*2mm", "个数": "120pcs", "不加税价格 (¥)": "14.45", "含税价格 (¥)": "21.67", "美元价格 ($)": "2.13", "库存": "有货", "口味/描述": "烟先生细长滤嘴 Smoking Slim Long Filter 6*22mm 120pcs"}, {"渠道": "华盛", "品牌": "老人牌", "种类": "滤嘴", "规格": "8*22mm 8*2mm", "个数": "150pcs", "不加税价格 (¥)": "14.58", "含税价格 (¥)": "21.87", "美元价格 ($)": "2.15", "库存": "有货", "口味/描述": "老人牌常规长滤嘴 Zig Zag Regular Long Filter 8*22mm 150pcs"}, {"渠道": "华盛", "品牌": "煙先生", "种类": "滤嘴", "规格": "8*22mm 8*2mm", "个数": "100pcs", "不加税价格 (¥)": "14.96", "含税价格 (¥)": "22.44", "美元价格 ($)": "2.20", "库存": "有货", "口味/描述": "烟先生常规长滤嘴 Smoking Filter Regular Long 8*22mm 100pcs"}, {"渠道": "华盛", "品牌": "ZEN", "种类": "滤嘴", "规格": "5mm 20mm", "个数": "200pcs", "不加税价格 (¥)": "16.06", "含税价格 (¥)": "24.09", "美元价格 ($)": "2.37", "库存": "无货", "口味/描述": "ZEN 滤嘴 ZEN Filter 200pcs 7.5mm x 20mm"}, {"渠道": "华盛", "品牌": "PURE", "种类": "滤嘴", "规格": "6*18mm 6*1mm", "个数": "200pcs", "不加税价格 (¥)": "18.90", "含税价格 (¥)": "28.35", "美元价格 ($)": "2.78", "库存": "有货", "口味/描述": "PURE 薄荷滤嘴 Pure Slims Menthol Filter 6*18mm 200pcs"}, {"渠道": "华盛", "品牌": "PURE", "种类": "滤嘴", "规格": "5.3*25mm 5.3*2mm", "个数": "200pcs", "不加税价格 (¥)": "18.90", "含税价格 (¥)": "28.35", "美元价格 ($)": "2.78", "库存": "有货", "口味/描述": "PURE 超细超长滤嘴 Pure Super Slims Long Filter 5.3*25mm 200pcs"}, {"渠道": "华盛", "品牌": "PURE", "种类": "滤嘴", "规格": "5.3*18mm 5.3*1mm", "个数": "200pcs", "不加税价格 (¥)": "18.90", "含税价格 (¥)": "28.35", "美元价格 ($)": "2.78", "库存": "有货", "口味/描述": "PURE 超细滤嘴 Pure Super Slims Filter 5.3*18mm 200pcs"}, {"渠道": "华盛", "品牌": "PURE", "种类": "滤嘴", "规格": "5.3*18mm 5.3*1mm", "个数": "200pcs", "不加税价格 (¥)": "18.90", "含税价格 (¥)": "28.35", "美元价格 ($)": "2.78", "库存": "有货", "口味/描述": "PURE 薄荷滤嘴 Pure Super Slims Menthol Filter 5.3*18mm 200pcs"}, {"渠道": "华盛", "品牌": "PURE", "种类": "滤嘴", "规格": "6*30mm 6*3mm", "个数": "200pcs", "不加税价格 (¥)": "20.70", "含税价格 (¥)": "31.05", "美元价格 ($)": "3.05", "库存": "有货", "口味/描述": "PURE 三倍活性炭细滤嘴 Pure Slims Triple Charcoal Filter 6*30mm 200pcs"}, {"渠道": "华盛", "品牌": "PURE", "种类": "滤嘴", "规格": "7.8*25mm 7.8*2mm", "个数": "150pcs", "不加税价格 (¥)": "20.70", "含税价格 (¥)": "31.05", "美元价格 ($)": "3.05", "库存": "有货", "口味/描述": "PURE 超长滤嘴 Pure Regular Super Long Filter 7.8*25mm 150pcs"}, {"渠道": "华盛", "品牌": "PURE", "种类": "滤嘴", "规格": "7.8*27mm 7.8*2mm", "个数": "120pcs", "不加税价格 (¥)": "20.70", "含税价格 (¥)": "31.05", "美元价格 ($)": "3.05", "库存": "有货", "口味/描述": "PURE 活性炭滤嘴 Pure Regular Charcoal Filter 7.8*27mm 120pcs"}, {"渠道": "华盛", "品牌": "PURE", "种类": "滤嘴", "规格": "6*25mm 6*2mm", "个数": "200pcs", "不加税价格 (¥)": "20.70", "含税价格 (¥)": "31.05", "美元价格 ($)": "3.05", "库存": "有货", "口味/描述": "PURE 活性炭细滤嘴 Pure Slims Charcoal Filter 6*25mm 200pcs"}, {"渠道": "华盛", "品牌": "PURE", "种类": "滤嘴", "规格": "5.3*30mm 5.3*3mm", "个数": "200pcs", "不加税价格 (¥)": "20.70", "含税价格 (¥)": "31.05", "美元价格 ($)": "3.05", "库存": "有货", "口味/描述": "PURE 活性炭滤嘴 Pure Super Slims Charcoal Filter 5.3*30mm 200pcs"}, {"渠道": "华盛", "品牌": "PURE", "种类": "滤嘴", "规格": "5.3*25mm 5.3*2mm", "个数": "200pcs", "不加税价格 (¥)": "20.70", "含税价格 (¥)": "31.05", "美元价格 ($)": "3.05", "库存": "有货", "口味/描述": "PURE 薄荷醇滤嘴 Pure Super Slims Long Thread Menthol Filter 5.3*25mm 200pcs"}, {"渠道": "华盛", "品牌": "PURE", "种类": "滤嘴", "规格": "6*25mm 6*2mm", "个数": "200pcs", "不加税价格 (¥)": "22.50", "含税价格 (¥)": "33.75", "美元价格 ($)": "3.31", "库存": "有货", "口味/描述": "PURE 留兰香细滤嘴 Pure Super Slims Long Spearmint Filter 6*25mm 200pcs"}, {"渠道": "华盛", "品牌": "PURE", "种类": "滤嘴", "规格": "6*25mm 6*2mm", "个数": "200pcs", "不加税价格 (¥)": "22.50", "含税价格 (¥)": "33.75", "美元价格 ($)": "3.31", "库存": "有货", "口味/描述": "PURE 柠檬细滤嘴 Pure Super Slims Long Lemon Lime Filter 6*25mm 200pcs"}, {"渠道": "华盛", "品牌": "PURE", "种类": "滤嘴", "规格": "6*25mm 6*2mm", "个数": "200pcs", "不加税价格 (¥)": "22.50", "含税价格 (¥)": "33.75", "美元价格 ($)": "3.31", "库存": "有货", "口味/描述": "PURE 樱桃细滤嘴 Pure Super Slims Long Cherry Filter 6*25mm 200pcs"}, {"渠道": "华盛", "品牌": "PURE", "种类": "滤嘴", "规格": "6*25mm 6*2mm", "个数": "200pcs", "不加税价格 (¥)": "22.50", "含税价格 (¥)": "33.75", "美元价格 ($)": "3.31", "库存": "有货", "口味/描述": "PURE 蓝莓薄荷细滤嘴 Pure Super Slims Long Berry Menthol Filter 6*25mm 200pcs"}, {"渠道": "华盛", "品牌": "PURE", "种类": "滤嘴", "规格": "6*25mm 6*2mm", "个数": "200pcs", "不加税价格 (¥)": "22.50", "含税价格 (¥)": "33.75", "美元价格 ($)": "3.31", "库存": "有货", "口味/描述": "PURE 香草细滤嘴 Pure Super Slims Long Vanilla Filter 6*25mm 200pcs"}, {"渠道": "华盛", "品牌": "PURE", "种类": "滤嘴", "规格": "6*30mm 6*3mm", "个数": "200pcs", "不加税价格 (¥)": "22.50", "含税价格 (¥)": "33.75", "美元价格 ($)": "3.31", "库存": "有货", "口味/描述": "PURE 超长细薄荷滤嘴 Pure Slims Extreme Long Menthol Filter 6*30mm 200pcs"}, {"渠道": "华盛", "品牌": "PURE", "种类": "滤嘴", "规格": "6*30mm 6*3mm", "个数": "200pcs", "不加税价格 (¥)": "22.50", "含税价格 (¥)": "33.75", "美元价格 ($)": "3.31", "库存": "有货", "口味/描述": "PURE 超长细滤嘴 Pure Slims Extreme Long Filter 6*30mm 200pcs"}, {"渠道": "华盛", "品牌": "PURE", "种类": "滤嘴", "规格": "6*24mm 6*2mm", "个数": "150pcs", "不加税价格 (¥)": "27.00", "含税价格 (¥)": "40.50", "美元价格 ($)": "3.98", "库存": "有货", "口味/描述": "PURE 薄荷爆珠细滤嘴 Pure Super Slims Long Crush Ice Menthol 6*24mm 150pcs"}, {"渠道": "华盛", "品牌": "PURE", "种类": "滤嘴", "规格": "5.3*30mm 5.3*3mm", "个数": "600pcs", "不加税价格 (¥)": "45.90", "含税价格 (¥)": "68.85", "美元价格 ($)": "6.76", "库存": "有货", "口味/描述": "PURE 活性炭细滤嘴 Pure Super Slims Charcoal Value Pack 5.3*30mm 600pcs"}, {"渠道": "华盛", "品牌": "切斯特菲尔德", "种类": "滤嘴", "规格": "", "个数": "", "不加税价格 (¥)": "263.65", "含税价格 (¥)": "395.47", "美元价格 ($)": "38.83", "库存": "库存仅剩 1", "口味/描述": "切斯特菲尔德活性炭过滤 Chesterfield Charcoal Filter  (1条10盒）"}, {"渠道": "华盛", "品牌": "云斯顿", "种类": "滤嘴", "规格": "", "个数": "", "不加税价格 (¥)": "364.34", "含税价格 (¥)": "546.51", "美元价格 ($)": "53.66", "库存": "无货", "口味/描述": "云斯顿红无滤嘴 Winston Filterless  (1条10盒）"}, {"渠道": "华盛", "品牌": "丰收", "种类": "卷纸", "规格": "70mm", "个数": "", "不加税价格 (¥)": "1.92", "含税价格 (¥)": "2.88", "美元价格 ($)": "0.28", "库存": "有货", "口味/描述": "丰收卷纸 Harvest Rolling Paper 70mm"}, {"渠道": "华盛", "品牌": "老人牌", "种类": "卷纸", "规格": "70mm", "个数": "50册", "不加税价格 (¥)": "2.24", "含税价格 (¥)": "3.36", "美元价格 ($)": "0.33", "库存": "有货", "口味/描述": "老人牌卷纸 Zig Zag Red Rolling Paper 70mm 50册/盒"}, {"渠道": "华盛", "品牌": "煙先生", "种类": "卷纸", "规格": "70mm", "个数": "", "不加税价格 (¥)": "2.27", "含税价格 (¥)": "3.41", "美元价格 ($)": "0.33", "库存": "有货", "口味/描述": "烟先生卷纸 Smoking Rolling Paper 70mm"}, {"渠道": "华盛", "品牌": "OCB", "种类": "卷纸", "规格": "70mm", "个数": "", "不加税价格 (¥)": "2.31", "含税价格 (¥)": "3.46", "美元价格 ($)": "0.34", "库存": "无货", "口味/描述": "OCB 蓝卷纸 OCB Blue Rolling Paper 70mm"}, {"渠道": "华盛", "品牌": "老人牌", "种类": "卷纸", "规格": "70mm", "个数": "50册", "不加税价格 (¥)": "2.36", "含税价格 (¥)": "3.54", "美元价格 ($)": "0.35", "库存": "有货", "口味/描述": "老人牌切角卷纸 Zig Zag Cut Corner Rolling Paper 70mm 50册/盒"}, {"渠道": "华盛", "品牌": "OCB", "种类": "卷纸", "规格": "70mm", "个数": "", "不加税价格 (¥)": "2.36", "含税价格 (¥)": "3.54", "美元价格 ($)": "0.35", "库存": "有货", "口味/描述": "OCB 慢燃黑卷纸 OCB Black Slowburn Rolling Paper 70mm"}, {"渠道": "华盛", "品牌": "天鹅", "种类": "卷纸", "规格": "70mm", "个数": "", "不加税价格 (¥)": "2.68", "含税价格 (¥)": "4.02", "美元价格 ($)": "0.39", "库存": "无货", "口味/描述": "天鹅绿卷纸 Swan Green Rolling Paper 70mm"}, {"渠道": "华盛", "品牌": "虎牌", "种类": "卷纸", "规格": "70mm", "个数": "", "不加税价格 (¥)": "2.68", "含税价格 (¥)": "4.02", "美元价格 ($)": "0.39", "库存": "有货", "口味/描述": "虎牌卷纸常规 Mascotte Regular Rolling Paper 70mm"}, {"渠道": "华盛", "品牌": "Rizla", "种类": "卷纸", "规格": "70mm", "个数": "", "不加税价格 (¥)": "3.96", "含税价格 (¥)": "5.94", "美元价格 ($)": "0.58", "库存": "无货", "口味/描述": "R+蓝慢燃卷纸 Rizla Blue Rolling Paper 70mm"}, {"渠道": "华盛", "品牌": "Rizla", "种类": "卷纸", "规格": "70mm", "个数": "", "不加税价格 (¥)": "3.96", "含税价格 (¥)": "5.94", "美元价格 ($)": "0.58", "库存": "无货", "口味/描述": "R+绿切角卷纸 Rizla Green Cut Corner Rolling Paper 70mm"}, {"渠道": "华盛", "品牌": "煙先生", "种类": "卷纸", "规格": "70mm", "个数": "", "不加税价格 (¥)": "4.10", "含税价格 (¥)": "6.15", "美元价格 ($)": "0.60", "库存": "有货", "口味/描述": "烟先生褐色未漂白卷纸 Smoking Brown No 8 Rolling Paper 70mm"}, {"渠道": "华盛", "品牌": "老人牌", "种类": "卷纸", "规格": "70mm", "个数": "25册", "不加税价格 (¥)": "4.82", "含税价格 (¥)": "7.23", "美元价格 ($)": "0.71", "库存": "有货", "口味/描述": "老人牌慢燃卷纸 Zig Zag Blue Slowburn Rolling Paper 70mm 25册/盒"}, {"渠道": "华盛", "品牌": "OCB", "种类": "卷纸", "规格": "78mm", "个数": "", "不加税价格 (¥)": "4.82", "含税价格 (¥)": "7.23", "美元价格 ($)": "0.71", "库存": "有货", "口味/描述": "OCB 慢燃黑卷纸 OCB Black Slowburn Rolling Paper 78mm"}, {"渠道": "华盛", "品牌": "黑马", "种类": "卷纸", "规格": "70mm", "个数": "50s", "不加税价格 (¥)": "4.97", "含税价格 (¥)": "7.46", "美元价格 ($)": "0.73", "库存": "有货", "口味/描述": "黑马甘草纸 Dark Horse Slowburn Licorice Paper 50s 70mm"}, {"渠道": "华盛", "品牌": "Raw", "种类": "卷纸", "规格": "70mm", "个数": "", "不加税价格 (¥)": "5.00", "含税价格 (¥)": "7.50", "美元价格 ($)": "0.74", "库存": "有货", "口味/描述": "Raw 慢燃卷纸 Single Wide Slowburn Paper 70mm"}, {"渠道": "华盛", "品牌": "舞女", "种类": "卷纸", "规格": "70mm", "个数": "100s", "不加税价格 (¥)": "5.52", "含税价格 (¥)": "8.28", "美元价格 ($)": "0.81", "库存": "无货", "口味/描述": "舞女切角卷纸 Marie Cut Corner Rolling Paper 100s 70mm"}, {"渠道": "华盛", "品牌": "RAW", "种类": "卷纸", "规格": "", "个数": "50张", "不加税价格 (¥)": "5.90", "含税价格 (¥)": "8.85", "美元价格 ($)": "0.87", "库存": "有货", "口味/描述": "RAW 黑宽50张/册 Raw Black Single Wide Paper"}, {"渠道": "华盛", "品牌": "煙先生", "种类": "卷纸", "规格": "70mm", "个数": "", "不加税价格 (¥)": "8.04", "含税价格 (¥)": "12.06", "美元价格 ($)": "1.18", "库存": "有货", "口味/描述": "烟先生甘草卷纸 Smoking Licorice Rolling Paper 70mm"}, {"渠道": "华盛", "品牌": "黑马", "种类": "空管", "规格": "8*15mm 8*1mm", "个数": "100s", "不加税价格 (¥)": "11.53", "含税价格 (¥)": "17.29", "美元价格 ($)": "1.70", "库存": "无货", "口味/描述": "黑马空管 Dark Horse Regular Filter Tubes 100s 8*15mm"}, {"渠道": "华盛", "品牌": "金冠", "种类": "空管", "规格": "5mm", "个数": "120pcs", "不加税价格 (¥)": "12.21", "含税价格 (¥)": "18.32", "美元价格 ($)": "1.80", "库存": "无货", "口味/描述": "金冠细空管 Korona Filter Tube 6.5mm 120pcs"}, {"渠道": "华盛", "品牌": "虎牌", "种类": "空管", "规格": "8*15mm 8*1mm", "个数": "100s", "不加税价格 (¥)": "13.57", "含税价格 (¥)": "20.36", "美元价格 ($)": "2.00", "库存": "有货", "口味/描述": "虎牌滤嘴空管 Mascotte filter tube 8*15mm 100s"}, {"渠道": "华盛", "品牌": "罗洛", "种类": "空管", "规格": "6.5*25mm 6.5*2mm", "个数": "100pcs", "不加税价格 (¥)": "14.84", "含税价格 (¥)": "22.26", "美元价格 ($)": "2.19", "库存": "有货", "口味/描述": "罗洛蓝空管 Rollo Blue Tube 6.5*25mm 100pcs"}, {"渠道": "华盛", "品牌": "罗洛", "种类": "空管", "规格": "6.5*25mm 6.5*2mm", "个数": "100pcs", "不加税价格 (¥)": "15.50", "含税价格 (¥)": "23.25", "美元价格 ($)": "2.28", "库存": "无货", "口味/描述": "罗洛薄荷空管 Rollo Green Mint Tube 6.5*25mm 100pcs"}, {"渠道": "华盛", "品牌": "黑马", "种类": "空管", "规格": "8*15mm 8*1mm", "个数": "100s", "不加税价格 (¥)": "17.75", "含税价格 (¥)": "26.62", "美元价格 ($)": "2.61", "库存": "无货", "口味/描述": "黑马碳滤嘴空管 Dark Horse Carbon Filter Tube 100s 8*15mm"}, {"渠道": "华盛", "品牌": "OCB", "种类": "空管", "规格": "8*24mm 8*2mm", "个数": "", "不加税价格 (¥)": "22.83", "含税价格 (¥)": "34.24", "美元价格 ($)": "3.36", "库存": "有货", "口味/描述": "OCB 特长滤嘴空管 OCB Extra Long Filter Tube 200’s 8*24mm"}, {"渠道": "华盛", "品牌": "虎牌", "种类": "空管", "规格": "8*24mm 8*2mm", "个数": "200s", "不加税价格 (¥)": "23.23", "含税价格 (¥)": "34.84", "美元价格 ($)": "3.42", "库存": "有货", "口味/描述": "虎牌特长滤嘴空管 Mascotte Extra Long Filter Tube 8*24mm 200s"}, {"渠道": "华盛", "品牌": "黑马", "种类": "空管", "规格": "8*24mm 8*2mm", "个数": "100s", "不加税价格 (¥)": "26.62", "含税价格 (¥)": "39.93", "美元价格 ($)": "3.92", "库存": "有货", "口味/描述": "黑马慢燃滤嘴空管 Dark Horse Cannatubes Filter Tube 8*24mm 100s"}, {"渠道": "华盛", "品牌": "黑马", "种类": "空管", "规格": "8*15mm 8*1mm", "个数": "", "不加税价格 (¥)": "26.62", "含税价格 (¥)": "39.93", "美元价格 ($)": "3.92", "库存": "有货", "口味/描述": "黑马黑棕滤嘴空管 Dark Horse Black Brown Filter Tube 8*15mm"}, {"渠道": "华盛", "品牌": "黑马", "种类": "空管", "规格": "8*24mm 8*2mm", "个数": "", "不加税价格 (¥)": "26.62", "含税价格 (¥)": "39.93", "美元价格 ($)": "3.92", "库存": "有货", "口味/描述": "黑马特长滤嘴空管 Dark Horse Extra Long Filter Tube 8*24mm"}, {"渠道": "华盛", "品牌": "黑马", "种类": "空管", "规格": "8*24mm 8*2mm", "个数": "", "不加税价格 (¥)": "36.94", "含税价格 (¥)": "55.41", "美元价格 ($)": "5.44", "库存": "无货", "口味/描述": "黑马特长碳滤嘴空管 Dark Horse Extra Long Carbon Filter Tube 8*24mm"}, {"渠道": "华盛", "品牌": "黑马", "种类": "空管", "规格": "8*24mm 8*2mm", "个数": "200s", "不加税价格 (¥)": "42.12", "含税价格 (¥)": "63.18", "美元价格 ($)": "6.20", "库存": "库存仅剩 3", "口味/描述": "黑马黑碳空管 Dark Horse Black Carbon Tube 8*24mm 200s"}, {"渠道": "华盛", "品牌": "黑马", "种类": "空管", "规格": "8*24mm 8*2mm", "个数": "", "不加税价格 (¥)": "44.38", "含税价格 (¥)": "66.57", "美元价格 ($)": "6.54", "库存": "无货", "口味/描述": "黑马碳铜空管 Dark Horse carbon copper Tube 8*24mm"}, {"渠道": "华盛", "品牌": "史丹利", "种类": "卷烟器", "规格": "", "个数": "", "不加税价格 (¥)": "15.44", "含税价格 (¥)": "23.16", "美元价格 ($)": "2.27", "库存": "有货", "口味/描述": "史丹利不可调节卷烟器 Stanley Non Adjustable Roller"}, {"渠道": "华盛", "品牌": "多明戈", "种类": "卷烟器", "规格": "", "个数": "", "不加税价格 (¥)": "16.91", "含税价格 (¥)": "25.37", "美元价格 ($)": "2.49", "库存": "有货", "口味/描述": "多明戈不可调节卷烟器 Domingo non adjustable Roller"}, {"渠道": "华盛", "品牌": "RAW", "种类": "卷烟器", "规格": "6*70mm", "个数": "", "不加税价格 (¥)": "17.98", "含税价格 (¥)": "26.97", "美元价格 ($)": "2.65", "库存": "有货", "口味/描述": "RAW 可调节卷烟器 RAW Adjustable Roller 8 / 6*70mm"}, {"渠道": "华盛", "品牌": "黑马", "种类": "卷烟器", "规格": "70mm", "个数": "", "不加税价格 (¥)": "23.20", "含税价格 (¥)": "34.80", "美元价格 ($)": "3.42", "库存": "无货", "口味/描述": "黑马可调节卷烟器 Dark Horse Adjustable Roller 70mm"}, {"渠道": "华盛", "品牌": "琥珀", "种类": "烟丝", "规格": "", "个数": "", "不加税价格 (¥)": "50.00", "含税价格 (¥)": "75.00", "美元价格 ($)": "7.36", "库存": "无货", "口味/描述": "琥珀 Amberleaf 30克 (限购- 每个订单限制1包）"}, {"渠道": "华盛", "品牌": "LD", "种类": "成品烟", "规格": "", "个数": "", "不加税价格 (¥)": "258.70", "含税价格 (¥)": "388.05", "美元价格 ($)": "38.10", "库存": "库存仅剩 2", "口味/描述": "LD薄荷 Liggett Ducat Menthol  (1条10盒）"}, {"渠道": "华盛", "品牌": "LD", "种类": "成品烟", "规格": "", "个数": "", "不加税价格 (¥)": "258.70", "含税价格 (¥)": "388.05", "美元价格 ($)": "38.10", "库存": "库存仅剩 3", "口味/描述": "LD蓝中免爆珠 Liggett Ducat Zoom Capsule  (1条10盒）"}, {"渠道": "华盛", "品牌": "LD", "种类": "成品烟", "规格": "", "个数": "", "不加税价格 (¥)": "258.70", "含税价格 (¥)": "388.05", "美元价格 ($)": "38.10", "库存": "库存仅剩 3", "口味/描述": "LD爆珠葡萄 Liggett Ducat Crush Grape  (1条10盒）"}, {"渠道": "华盛", "品牌": "LD", "种类": "成品烟", "规格": "", "个数": "", "不加税价格 (¥)": "259.00", "含税价格 (¥)": "388.50", "美元价格 ($)": "38.14", "库存": "库存仅剩 2", "口味/描述": "LD红 Liggett Ducat Red (1条10盒）"}, {"渠道": "华盛", "品牌": "LD", "种类": "成品烟", "规格": "", "个数": "", "不加税价格 (¥)": "259.00", "含税价格 (¥)": "388.50", "美元价格 ($)": "38.14", "库存": "库存仅剩 2", "口味/描述": "LD蓝 Liggett Ducat Blue  (1条10盒）"}, {"渠道": "华盛", "品牌": "切斯特菲尔德", "种类": "成品烟", "规格": "", "个数": "", "不加税价格 (¥)": "263.65", "含税价格 (¥)": "395.47", "美元价格 ($)": "38.83", "库存": "库存仅剩 2", "口味/描述": "切斯特菲尔德薄荷 Chesterfield Menthol  (1条10盒）"}, {"渠道": "华盛", "品牌": "切斯特菲尔德", "种类": "成品烟", "规格": "", "个数": "", "不加税价格 (¥)": "263.65", "含税价格 (¥)": "395.47", "美元价格 ($)": "38.83", "库存": "库存仅剩 2", "口味/描述": "切斯特菲尔德紫色 Chesterfield Purple  (1条10盒）"}, {"渠道": "华盛", "品牌": "切斯特菲尔德", "种类": "成品烟", "规格": "", "个数": "", "不加税价格 (¥)": "263.65", "含税价格 (¥)": "395.47", "美元价格 ($)": "38.83", "库存": "库存仅剩 2", "口味/描述": "切斯特菲尔德蓝 Chesterfield Blue  (1条10盒）"}, {"渠道": "华盛", "品牌": "Terea", "种类": "成品烟", "规格": "", "个数": "", "不加税价格 (¥)": "266.40", "含税价格 (¥)": "399.60", "美元价格 ($)": "39.23", "库存": "库存仅剩 2", "口味/描述": "Terea 桑葚丁香 Kretek Mulberry (一条10盒）"}, {"渠道": "华盛", "品牌": "Terea", "种类": "成品烟", "规格": "", "个数": "", "不加税价格 (¥)": "266.40", "含税价格 (¥)": "399.60", "美元价格 ($)": "39.23", "库存": "库存仅剩 2", "口味/描述": "Terea 星光 Starling (一条10盒）"}, {"渠道": "华盛", "品牌": "Terea", "种类": "成品烟", "规格": "", "个数": "", "不加税价格 (¥)": "266.40", "含税价格 (¥)": "399.60", "美元价格 ($)": "39.23", "库存": "库存仅剩 3", "口味/描述": "Terea 太阳爆珠 Sun Pearl (一条10盒）"}, {"渠道": "华盛", "品牌": "Terea", "种类": "成品烟", "规格": "", "个数": "", "不加税价格 (¥)": "266.40", "含税价格 (¥)": "399.60", "美元价格 ($)": "39.23", "库存": "库存仅剩 3", "口味/描述": "Terea 绿洲爆珠 Oasis Pearl (一条10盒）"}, {"渠道": "华盛", "品牌": "Terea", "种类": "成品烟", "规格": "", "个数": "", "不加税价格 (¥)": "266.40", "含税价格 (¥)": "399.60", "美元价格 ($)": "39.23", "库存": "库存仅剩 3", "口味/描述": "Terea 青柠薄荷 Zing Wave (一条10盒）"}, {"渠道": "华盛", "品牌": "Terea", "种类": "成品烟", "规格": "", "个数": "", "不加税价格 (¥)": "266.40", "含税价格 (¥)": "399.60", "美元价格 ($)": "39.23", "库存": "库存仅剩 3", "口味/描述": "Terea 蓝莓薄荷 Purple Wave (一条10盒）"}, {"渠道": "华盛", "品牌": "Terea", "种类": "成品烟", "规格": "", "个数": "", "不加税价格 (¥)": "266.40", "含税价格 (¥)": "399.60", "美元价格 ($)": "39.23", "库存": "库存仅剩 2", "口味/描述": "Terea 淡薄荷 Turquoise (一条10盒）"}, {"渠道": "华盛", "品牌": "Terea", "种类": "成品烟", "规格": "", "个数": "", "不加税价格 (¥)": "266.40", "含税价格 (¥)": "399.60", "美元价格 ($)": "39.23", "库存": "有货", "口味/描述": "Terea 浓薄荷 Blue (一条10盒）"}, {"渠道": "华盛", "品牌": "Terea", "种类": "成品烟", "规格": "", "个数": "", "不加税价格 (¥)": "266.40", "含税价格 (¥)": "399.60", "美元价格 ($)": "39.23", "库存": "库存仅剩 2", "口味/描述": "Terea 琥珀原味 Amber (一条10盒）"}, {"渠道": "华盛", "品牌": "Terea", "种类": "成品烟", "规格": "", "个数": "", "不加税价格 (¥)": "266.40", "含税价格 (¥)": "399.60", "美元价格 ($)": "39.23", "库存": "库存仅剩 2", "口味/描述": "Terea 深原味 Sienna (一条10盒）"}, {"渠道": "华盛", "品牌": "Terea", "种类": "成品烟", "规格": "", "个数": "", "不加税价格 (¥)": "266.40", "含税价格 (¥)": "399.60", "美元价格 ($)": "39.23", "库存": "库存仅剩 3", "口味/描述": "Terea 浓原味 Russet (一条10盒）"}, {"渠道": "华盛", "品牌": "Terea", "种类": "成品烟", "规格": "", "个数": "", "不加税价格 (¥)": "266.40", "含税价格 (¥)": "399.60", "美元价格 ($)": "39.23", "库存": "库存仅剩 3", "口味/描述": "Terea 极冷柑橘 Black Yellow (一条10盒）"}, {"渠道": "华盛", "品牌": "Terea", "种类": "成品烟", "规格": "", "个数": "", "不加税价格 (¥)": "266.40", "含税价格 (¥)": "399.60", "美元价格 ($)": "39.23", "库存": "库存仅剩 1", "口味/描述": "Terea 极冷蓝莓薄荷 Black Purple Mint(一条10盒）"}, {"渠道": "华盛", "品牌": "Terea", "种类": "成品烟", "规格": "", "个数": "", "不加税价格 (¥)": "266.40", "含税价格 (¥)": "399.60", "美元价格 ($)": "39.23", "库存": "库存仅剩 2", "口味/描述": "Terea 极冷薄荷 Black Green (一条10盒）"}, {"渠道": "华盛", "品牌": "云斯顿", "种类": "成品烟", "规格": "", "个数": "", "不加税价格 (¥)": "346.98", "含税价格 (¥)": "520.47", "美元价格 ($)": "51.10", "库存": "库存仅剩 2", "口味/描述": "云斯顿蓝 Winston Blue  (1条10盒）"}, {"渠道": "华盛", "品牌": "云斯顿", "种类": "成品烟", "规格": "", "个数": "", "不加税价格 (¥)": "346.98", "含税价格 (¥)": "520.47", "美元价格 ($)": "51.10", "库存": "库存仅剩 4", "口味/描述": "云斯顿双重爆珠 Winston Duo Capsule  (1条10盒）"}, {"渠道": "华盛", "品牌": "云斯顿", "种类": "成品烟", "规格": "", "个数": "", "不加税价格 (¥)": "346.98", "含税价格 (¥)": "520.47", "美元价格 ($)": "51.10", "库存": "库存仅剩 1", "口味/描述": "云斯顿红 Winston Red  (1条10盒）"}, {"渠道": "华盛", "品牌": "梅维乌斯", "种类": "成品烟", "规格": "", "个数": "", "不加税价格 (¥)": "347.90", "含税价格 (¥)": "521.85", "美元价格 ($)": "51.24", "库存": "库存仅剩 4", "口味/描述": "梅维乌斯双冰 Mevius Double Ice (1条10盒）"}, {"渠道": "华盛", "品牌": "梅维乌斯", "种类": "成品烟", "规格": "", "个数": "", "不加税价格 (¥)": "347.90", "含税价格 (¥)": "521.85", "美元价格 ($)": "51.24", "库存": "库存仅剩 2", "口味/描述": "梅维乌斯爆珠 Mevius Capsule  (1条10盒）"}, {"渠道": "华盛", "品牌": "梅维乌斯", "种类": "成品烟", "规格": "", "个数": "", "不加税价格 (¥)": "347.90", "含税价格 (¥)": "521.85", "美元价格 ($)": "51.24", "库存": "库存仅剩 2", "口味/描述": "梅维乌斯斯极 Mevius Kiwami  (1条10盒）"}, {"渠道": "华盛", "品牌": "梅维乌斯", "种类": "成品烟", "规格": "", "个数": "", "不加税价格 (¥)": "347.90", "含税价格 (¥)": "521.85", "美元价格 ($)": "51.24", "库存": "库存仅剩 2", "口味/描述": "梅维乌斯薄荷白 Mevius Menthol White  (1条10盒）"}, {"渠道": "华盛", "品牌": "梅维乌斯", "种类": "成品烟", "规格": "", "个数": "", "不加税价格 (¥)": "347.90", "含税价格 (¥)": "521.85", "美元价格 ($)": "51.24", "库存": "有货", "口味/描述": "梅维乌斯薄荷 Mevius Menthol  (1条10盒）"}, {"渠道": "华盛", "品牌": "梅维乌斯", "种类": "成品烟", "规格": "", "个数": "", "不加税价格 (¥)": "347.90", "含税价格 (¥)": "521.85", "美元价格 ($)": "51.24", "库存": "库存仅剩 1", "口味/描述": "梅维乌斯风蓝 Mevius Wind Blue  (1条10盒）"}, {"渠道": "华盛", "品牌": "梅维乌斯", "种类": "成品烟", "规格": "", "个数": "", "不加税价格 (¥)": "347.90", "含税价格 (¥)": "521.85", "美元价格 ($)": "51.24", "库存": "库存仅剩 3", "口味/描述": "梅维乌斯黄 Mevius Yellow (1条10盒）"}, {"渠道": "华盛", "品牌": "梅维乌斯", "种类": "成品烟", "规格": "", "个数": "", "不加税价格 (¥)": "349.16", "含税价格 (¥)": "523.74", "美元价格 ($)": "51.42", "库存": "库存仅剩 3", "口味/描述": "梅维乌斯天蓝 Mevius Sky Blue  (1条10盒）"}, {"渠道": "华盛", "品牌": "梅维乌斯", "种类": "成品烟", "规格": "", "个数": "", "不加税价格 (¥)": "349.16", "含税价格 (¥)": "523.74", "美元价格 ($)": "51.42", "库存": "库存仅剩 3", "口味/描述": "梅维乌斯原味 Mevius Original  (1条10盒）"}, {"渠道": "华盛", "品牌": "登喜路", "种类": "成品烟", "规格": "", "个数": "", "不加税价格 (¥)": "353.30", "含税价格 (¥)": "529.95", "美元价格 ($)": "52.03", "库存": "库存仅剩 1", "口味/描述": "登喜路红 Dunhill Red (1条10盒)"}, {"渠道": "华盛", "品牌": "登喜路", "种类": "成品烟", "规格": "", "个数": "", "不加税价格 (¥)": "353.30", "含税价格 (¥)": "529.95", "美元价格 ($)": "52.03", "库存": "库存仅剩 2", "口味/描述": "登喜路热情黄 Dunhill Zest Yellow  (1条10盒）"}, {"渠道": "华盛", "品牌": "登喜路", "种类": "成品烟", "规格": "", "个数": "", "不加税价格 (¥)": "353.30", "含税价格 (¥)": "529.95", "美元价格 ($)": "52.03", "库存": "库存仅剩 1", "口味/描述": "登喜路深蓝(混合) Dunhill Dark Blue BCF (Mix)  (1条10盒）"}, {"渠道": "华盛", "品牌": "登喜路", "种类": "成品烟", "规格": "", "个数": "", "不加税价格 (¥)": "353.30", "含税价格 (¥)": "529.95", "美元价格 ($)": "52.03", "库存": "库存仅剩 1", "口味/描述": "登喜路香槟 Dunhill Champagne  (1条10盒）"}, {"渠道": "华盛", "品牌": "登喜路", "种类": "成品烟", "规格": "", "个数": "", "不加税价格 (¥)": "353.30", "含税价格 (¥)": "529.95", "美元价格 ($)": "52.03", "库存": "库存仅剩 2", "口味/描述": "登喜路深绿色(增强) Dunhill Dark Green (Boost)  (1条10盒）"}, {"渠道": "华盛", "品牌": "登喜路", "种类": "成品烟", "规格": "", "个数": "", "不加税价格 (¥)": "353.30", "含税价格 (¥)": "529.95", "美元价格 ($)": "52.03", "库存": "库存仅剩 3", "口味/描述": "登喜路经典 Dunhill Evo Classic (1条10盒）"}, {"渠道": "华盛", "品牌": "登喜路", "种类": "成品烟", "规格": "", "个数": "", "不加税价格 (¥)": "353.30", "含税价格 (¥)": "529.95", "美元价格 ($)": "52.03", "库存": "库存仅剩 2", "口味/描述": "登喜路薄荷 Dunhill Menthol  (1条10盒）"}, {"渠道": "华盛", "品牌": "登喜路", "种类": "成品烟", "规格": "", "个数": "", "不加税价格 (¥)": "353.30", "含税价格 (¥)": "529.95", "美元价格 ($)": "52.03", "库存": "库存仅剩 1", "口味/描述": "登喜路浅蓝 Dunhill Light Blue  (1条10盒）"}, {"渠道": "华盛", "品牌": "万宝路", "种类": "成品烟", "规格": "", "个数": "", "不加税价格 (¥)": "355.76", "含税价格 (¥)": "533.64", "美元价格 ($)": "52.39", "库存": "库存仅剩 2", "口味/描述": "万宝路白金 Marlboro Gold  (1条10盒）"}, {"渠道": "华盛", "品牌": "万宝路", "种类": "成品烟", "规格": "", "个数": "", "不加税价格 (¥)": "355.76", "含税价格 (¥)": "533.64", "美元价格 ($)": "52.39", "库存": "库存仅剩 3", "口味/描述": "万宝路维斯塔黑薄荷 Marlboro Vista Black Mint  (1条10盒）"}, {"渠道": "华盛", "品牌": "万宝路", "种类": "成品烟", "规格": "", "个数": "", "不加税价格 (¥)": "355.76", "含税价格 (¥)": "533.64", "美元价格 ($)": "52.39", "库存": "库存仅剩 3", "口味/描述": "万宝路维斯塔热带飞溅 Marlboro Vista Tropical Splash  (1条10盒）"}, {"渠道": "华盛", "品牌": "万宝路", "种类": "成品烟", "规格": "", "个数": "", "不加税价格 (¥)": "355.76", "含税价格 (¥)": "533.64", "美元价格 ($)": "52.39", "库存": "库存仅剩 1", "口味/描述": "万宝路维斯塔夏日狂欢 Marlboro Vista Summer Splash  (1条10盒）"}, {"渠道": "华盛", "品牌": "万宝路", "种类": "成品烟", "规格": "", "个数": "", "不加税价格 (¥)": "355.76", "含税价格 (¥)": "533.64", "美元价格 ($)": "52.39", "库存": "库存仅剩 3", "口味/描述": "万宝路维斯塔薄荷 Marlboro Vista Menthol  (1条10盒）"}, {"渠道": "华盛", "品牌": "万宝路", "种类": "成品烟", "规格": "", "个数": "", "不加税价格 (¥)": "355.76", "含税价格 (¥)": "533.64", "美元价格 ($)": "52.39", "库存": "库存仅剩 3", "口味/描述": "万宝路维斯塔冰爆珠 Marlboro Vista Ice Blast  (1条10盒）"}, {"渠道": "华盛", "品牌": "万宝路", "种类": "成品烟", "规格": "", "个数": "", "不加税价格 (¥)": "355.76", "含税价格 (¥)": "533.64", "美元价格 ($)": "52.39", "库存": "库存仅剩 5", "口味/描述": "万宝路维斯塔双爆 Marlboro Vista Double Burst  (1条10盒）"}, {"渠道": "华盛", "品牌": "万宝路", "种类": "成品烟", "规格": "", "个数": "", "不加税价格 (¥)": "355.76", "含税价格 (¥)": "533.64", "美元价格 ($)": "52.39", "库存": "库存仅剩 2", "口味/描述": "万宝路硬红 Marlboro Hard Red (1条10盒）"}, {"渠道": "华盛", "品牌": "切斯特菲尔德", "种类": "成品烟", "规格": "", "个数": "", "不加税价格 (¥)": "371.70", "含税价格 (¥)": "557.55", "美元价格 ($)": "54.74", "库存": "库存仅剩 2", "口味/描述": "切斯特菲尔德红 Chesterfield Red  (1条10盒）"}, {"渠道": "华盛", "品牌": "手卷新手精选", "种类": "套装", "规格": "", "个数": "", "不加税价格 (¥)": "530.00", "含税价格 (¥)": "795.00", "美元价格 ($)": "78.06", "库存": "有货", "口味/描述": "手卷新手精选 RYO Special Selection SET 1"}]